bagel_factor/__init__.py
bagel_factor/evaluator.py
bagel_factor/data_handling/__init__.py
bagel_factor/data_handling/factor_data.py
bagel_factor/data_handling/preprocessing.py
bagel_factor/metrics/__init__.py
bagel_factor/metrics/ic.py
bagel_factor/metrics/quantile_returns.py
bagel_factor/metrics/risk_metrics.py
bagel_factor/visualization/__init__.py
bagel_factor/visualization/plots.py
bagel_factor-2.0.1.dist-info/licenses/LICENSE
bagel_factor-2.0.1.dist-info/METADATA
bagel_factor-2.0.1.dist-info/WHEEL
bagel_factor-2.0.1.dist-info/top_level.txt
bagel_factor-2.0.1.dist-info/RECORD
