Metadata-Version: 2.4
Name: bagel-factor
Version: 2.0.1
Summary: Bagel Factor is a Python package for factor analysis
Author-email: Yanzhong Huang <eric.yanzhong.huang@gmail.com>
Project-URL: Homepage, https://github.com/bagelquant/bagel-factor
Project-URL: Issues, https://github.com/bagelquant/bagel-factor/issues
Classifier: Programming Language :: Python :: 3
Classifier: License :: OSI Approved :: MIT License
Classifier: Operating System :: OS Independent
Requires-Python: >=3.10
License-File: LICENSE
Requires-Dist: numpy>=2.2.0
Requires-Dist: pandas>=2.2.0
Requires-Dist: statsmodels>=0.14.0
Requires-Dist: matplotlib>=3.10.0
Requires-Dist: seaborn>=0.13.0
Dynamic: license-file
